{ "compressionlevel":-1,
 "height":10,
 "infinite":false,
 "layers":[
        {
         "id":3,
         "layers":[
                {
                 "data":[12, 12, 12, 12, 12, 12, 12, 12, 12, 12, 12, 12, 12, 12, 12,
                    12, 12, 12, 12, 12, 12, 12, 12, 12, 12, 12, 12, 12, 12, 12,
                    12, 12, 12, 12, 12, 12, 12, 43, 12, 12, 12, 12, 12, 12, 12,
                    12, 12, 12, 12, 12, 12, 43, 43, 43, 12, 12, 12, 12, 12, 12,
                    12, 12, 12, 12, 12, 43, 43, 43, 43, 43, 12, 12, 12, 12, 12,
                    12, 12, 12, 12, 12, 43, 43, 43, 43, 43, 12, 12, 12, 12, 12,
                    12, 12, 12, 12, 12, 12, 43, 12, 43, 12, 12, 12, 12, 12, 12,
                    12, 12, 12, 12, 12, 12, 12, 12, 12, 12, 12, 12, 12, 12, 12,
                    12, 12, 12, 12, 12, 12, 12, 12, 12, 12, 12, 12, 12, 12, 12,
                    12, 12, 12, 12, 12, 12, 12, 12, 12, 12, 12, 12, 12, 12, 12],
                 "height":10,
                 "id":1,
                 "name":"Tiles",
                 "opacity":1,
                 "type":"tilelayer",
                 "visible":true,
                 "width":15,
                 "x":0,
                 "y":0
                }],
         "name":"Terrain",
         "opacity":1,
         "type":"group",
         "visible":true,
         "x":0,
         "y":0
        }, 
        {
         "id":4,
         "layers":[
                {
                 "draworder":"topdown",
                 "id":5,
                 "name":"Player",
                 "objects":[
                        {
                         "gid":51,
                         "height":64,
                         "id":11,
                         "name":"",
                         "rotation":0,
                         "type":"",
                         "visible":true,
                         "width":64,
                         "x":0,
                         "y":640
                        }],
                 "opacity":1,
                 "type":"objectgroup",
                 "visible":true,
                 "x":0,
                 "y":0
                }, 
                {
                 "draworder":"topdown",
                 "id":2,
                 "name":"Emitters",
                 "objects":[
                        {
                         "gid":30,
                         "height":64,
                         "id":3,
                         "name":"",
                         "properties":[
                                {
                                 "name":"EmitterOutputType",
                                 "propertytype":"EmitterOutputType",
                                 "type":"string",
                                 "value":"T_JUNCTION"
                                }, 
                                {
                                 "name":"EmitterSubtype",
                                 "propertytype":"EmitterSubtype",
                                 "type":"string",
                                 "value":"Basic"
                                }],
                         "rotation":0,
                         "type":"EmitterEntity",
                         "visible":true,
                         "width":64,
                         "x":640,
                         "y":256
                        }, 
                        {
                         "gid":30,
                         "height":64,
                         "id":4,
                         "name":"",
                         "properties":[
                                {
                                 "name":"EmitterOutputType",
                                 "propertytype":"EmitterOutputType",
                                 "type":"string",
                                 "value":"T_JUNCTION"
                                }, 
                                {
                                 "name":"EmitterSubtype",
                                 "propertytype":"EmitterSubtype",
                                 "type":"string",
                                 "value":"Basic"
                                }],
                         "rotation":180,
                         "type":"EmitterEntity",
                         "visible":true,
                         "width":64,
                         "x":320,
                         "y":192
                        }, 
                        {
                         "gid":52,
                         "height":64,
                         "id":5,
                         "name":"",
                         "properties":[
                                {
                                 "name":"EmitterOutputType",
                                 "propertytype":"EmitterOutputType",
                                 "type":"string",
                                 "value":"L_CURVE"
                                }, 
                                {
                                 "name":"EmitterSubtype",
                                 "propertytype":"EmitterSubtype",
                                 "type":"string",
                                 "value":"Basic"
                                }],
                         "rotation":90,
                         "type":"EmitterEntity",
                         "visible":true,
                         "width":64,
                         "x":448,
                         "y":64
                        }, 
                        {
                         "gid":40,
                         "height":64,
                         "id":7,
                         "name":"",
                         "properties":[
                                {
                                 "name":"EmitterOutputType",
                                 "propertytype":"EmitterOutputType",
                                 "type":"string",
                                 "value":"DOUBLE"
                                }, 
                                {
                                 "name":"EmitterSubtype",
                                 "propertytype":"EmitterSubtype",
                                 "type":"string",
                                 "value":"Basic"
                                }],
                         "rotation":-90,
                         "type":"EmitterEntity",
                         "visible":true,
                         "width":64,
                         "x":512,
                         "y":512
                        }, 
                        {
                         "gid":25,
                         "height":64,
                         "id":8,
                         "name":"",
                         "properties":[
                                {
                                 "name":"EmitterOutputType",
                                 "propertytype":"EmitterOutputType",
                                 "type":"string",
                                 "value":"SINGLE"
                                }, 
                                {
                                 "name":"EmitterSubtype",
                                 "propertytype":"EmitterSubtype",
                                 "type":"string",
                                 "value":"Basic"
                                }],
                         "rotation":-90,
                         "type":"EmitterEntity",
                         "visible":true,
                         "width":64,
                         "x":832,
                         "y":384
                        }, 
                        {
                         "gid":33,
                         "height":64,
                         "id":9,
                         "name":"",
                         "properties":[
                                {
                                 "name":"EmitterOutputType",
                                 "propertytype":"EmitterOutputType",
                                 "type":"string",
                                 "value":"QUAD"
                                }, 
                                {
                                 "name":"EmitterSubtype",
                                 "propertytype":"EmitterSubtype",
                                 "type":"string",
                                 "value":"Basic"
                                }],
                         "rotation":0,
                         "type":"EmitterEntity",
                         "visible":true,
                         "width":64,
                         "x":128,
                         "y":384
                        }, 
                        {
                         "gid":20,
                         "height":64,
                         "id":15,
                         "name":"",
                         "properties":[
                                {
                                 "name":"EmitterOutputType",
                                 "propertytype":"EmitterOutputType",
                                 "type":"string",
                                 "value":"J_CURVE"
                                }, 
                                {
                                 "name":"EmitterSubtype",
                                 "propertytype":"EmitterSubtype",
                                 "type":"string",
                                 "value":"Basic"
                                }],
                         "rotation":0,
                         "type":"EmitterEntity",
                         "visible":true,
                         "width":64,
                         "x":384,
                         "y":128
                        }, 
                        {
                         "gid":31,
                         "height":64,
                         "id":17,
                         "name":"",
                         "properties":[
                                {
                                 "name":"EmitterOutputType",
                                 "propertytype":"EmitterOutputType",
                                 "type":"string",
                                 "value":"DOUBLE"
                                }, 
                                {
                                 "name":"EmitterSubtype",
                                 "propertytype":"EmitterSubtype",
                                 "type":"string",
                                 "value":"Splitter"
                                }],
                         "rotation":0,
                         "type":"EmitterEntity",
                         "visible":true,
                         "width":64,
                         "x":256,
                         "y":512
                        }, 
                        {
                         "gid":31,
                         "height":64,
                         "id":18,
                         "name":"",
                         "properties":[
                                {
                                 "name":"EmitterOutputType",
                                 "propertytype":"EmitterOutputType",
                                 "type":"string",
                                 "value":"SINGLE"
                                }, 
                                {
                                 "name":"EmitterSubtype",
                                 "propertytype":"EmitterSubtype",
                                 "type":"string",
                                 "value":"Splitter"
                                }],
                         "rotation":0,
                         "type":"EmitterEntity",
                         "visible":true,
                         "width":64,
                         "x":640,
                         "y":512
                        }],
                 "opacity":1,
                 "type":"objectgroup",
                 "visible":true,
                 "x":0,
                 "y":0
                }],
         "name":"Entities",
         "opacity":1,
         "type":"group",
         "visible":true,
         "x":0,
         "y":0
        }],
 "nextlayerid":6,
 "nextobjectid":25,
 "orientation":"orthogonal",
 "renderorder":"left-up",
 "tiledversion":"1.10.2",
 "tileheight":64,
 "tilesets":[
        {
         "firstgid":1,
         "source":"..\/..\/..\/..\/..\/spritework\/test\/test_tileset.tsx"
        }, 
        {
         "firstgid":1,
         "source":"Tileset_sample.tsx"
        }],
 "tilewidth":64,
 "type":"map",
 "version":"1.10",
 "width":15
}